LICENSE
MANIFEST.in
README.md
setup.py
em_map_utils/__init__.py
em_map_utils/download_emdb.py
em_map_utils/farm_function.py
em_map_utils/filled_cuboid.py
em_map_utils/filled_cylinder.py
em_map_utils/filled_sphere.py
em_map_utils/map_covariance.py
em_map_utils/map_line_projections.py
em_map_utils/map_rotate.py
em_map_utils/map_threshold.py
em_map_utils/structure_size_and_shape.py
em_map_utils/util.py
em_map_utils.egg-info/PKG-INFO
em_map_utils.egg-info/SOURCES.txt
em_map_utils.egg-info/dependency_links.txt
em_map_utils.egg-info/top_level.txt
em_map_utils/demos/__init__.py
em_map_utils/demos/demo_farm_function.py
em_map_utils/demos/demo_filled_cuboid.py
em_map_utils/demos/demo_filled_cylinder.py
em_map_utils/demos/demo_filled_sphere.py
em_map_utils/demos/demo_map_covariance.py
em_map_utils/demos/demo_map_line_projections.py
em_map_utils/demos/demo_map_rotate.py
em_map_utils/demos/ortho_surface_views.py